ce2.py
ce2-0.1.0.dist-info/LICENSE
ce2-0.1.0.dist-info/METADATA
ce2-0.1.0.dist-info/WHEEL
ce2-0.1.0.dist-info/entry_points.txt
ce2-0.1.0.dist-info/top_level.txt
ce2-0.1.0.dist-info/RECORD
