Metadata-Version: 2.1
Name: ce2
Version: 0.1.0
Summary: The Cost Explorer Explorer
Home-page: https://github.com/sirosen/ce2
Author: Stephen Rosen
Author-email: sirosen@uchicago.edu
License: UNKNOWN
Platform: UNKNOWN
Classifier: Development Status :: 3 - Alpha
Classifier: Intended Audience :: Developers
Classifier: License :: OSI Approved :: Apache Software License
Classifier: Programming Language :: Python :: 3
Requires-Python: >=3.6.2
Requires-Dist: boto3
